py15_9199/10a.py
py15_9199/2a.py
py15_9199/3a.py
py15_9199/4a.py
py15_9199/5a.py
py15_9199/6a.py
py15_9199/7a.py
py15_9199/8a.py
py15_9199/9a.py
py15_9199/__init__.py
py15_9199-0.1.0.dist-info/METADATA
py15_9199-0.1.0.dist-info/WHEEL
py15_9199-0.1.0.dist-info/top_level.txt
py15_9199-0.1.0.dist-info/RECORD
